theo_velux_remote_control/__init__.py
theo_velux_remote_control/__main__.py
theo_velux_remote_control/cli.py
theo_velux_remote_control/config.py
theo_velux_remote_control/velux.py
theo_velux_remote_control-1.0.3.dist-info/METADATA
theo_velux_remote_control-1.0.3.dist-info/WHEEL
theo_velux_remote_control-1.0.3.dist-info/entry_points.txt
theo_velux_remote_control-1.0.3.dist-info/RECORD
