Metadata-Version: 2.3
Name: theo-velux-remote-control
Version: 1.0.3
Summary: Small package to open, close, stop Velux shutters, includes a CLI. Requires wiring of a Velux remote control.
Author: Theo-Dancoisne
Requires-Python: >=3.9
Classifier: Programming Language :: Python :: 3
Classifier: Programming Language :: Python :: 3.9
Classifier: Programming Language :: Python :: 3.10
Classifier: Programming Language :: Python :: 3.11
Classifier: Programming Language :: Python :: 3.12
Classifier: Programming Language :: Python :: 3.13
Requires-Dist: python-dotenv (>=1.1.0)
Requires-Dist: rpi-gpio (>=0.7.1)
Requires-Dist: typer (>=0.15.2)
